battleship/__init__.py
battleship/parser.py
battleship/server.py
battleship/engine/__init__.py
battleship/engine/util.py
battleship_python-0.0.1.dist-info/LICENSE
battleship_python-0.0.1.dist-info/METADATA
battleship_python-0.0.1.dist-info/WHEEL
battleship_python-0.0.1.dist-info/top_level.txt
battleship_python-0.0.1.dist-info/RECORD
